gpalexp/__init__.py
gpalexp/gpal_optimize.py
gpalexp/gpal_plot.py
gpalexp/gpr_fit_predict.py
gpalexp/gpr_instance.py
gpalexp/utils.py
gpalexp-0.1.10.5.dist-info/METADATA
gpalexp-0.1.10.5.dist-info/WHEEL
gpalexp-0.1.10.5.dist-info/licenses/LICENSE
gpalexp-0.1.10.5.dist-info/RECORD
