Metadata-Version: 2.4
Name: GPALexp
Version: 0.1.10.5
Summary: A package for incorporating Gaussian Process Active Learning (GPAL) in psychology experiments.
Project-URL: Homepage, https://github.com/KAIST-PAI-lab/GPALexp
Project-URL: Issues, https://github.com/KAIST-PAI-lab/GPALexp/issues
Author-email: Junyup Kim <ytrewq271828@kaist.ac.kr>, Chaeho Lee <chaeholee@kaist.ac.kr>, Boyoung Kwon <bykwon@kaist.ac.kr>, Sangho Lee <sangholee@kaist.ac.kr>
Maintainer-email: Junyup Kim <ytrewq271828@alumni.kaist.ac.kr>, Sangho Lee <sangholee@kaist.ac.kr>
License-Expression: GPL-3.0-or-later
License-File: LICENSE
Classifier: Intended Audience :: Science/Research
Classifier: License :: OSI Approved :: GNU General Public License v3 or later (GPLv3+)
Classifier: Natural Language :: English
Classifier: Operating System :: Microsoft :: Windows :: Windows 11
Classifier: Programming Language :: Python :: 3.10
Classifier: Topic :: Software Development :: Version Control :: Git
Requires-Python: ==3.10.*
Requires-Dist: matplotlib==3.10.3
Requires-Dist: numpy==2.2.6
Requires-Dist: pandas==2.3.1
Requires-Dist: scikit-learn==1.7.1
Requires-Dist: scipy==1.15.3
